accfifo/__init__.py
accfifo-0.2.0.dist-info/LICENSE.txt
accfifo-0.2.0.dist-info/METADATA
accfifo-0.2.0.dist-info/WHEEL
accfifo-0.2.0.dist-info/top_level.txt
accfifo-0.2.0.dist-info/RECORD
