Metadata-Version: 2.1
Name: accfifo
Version: 0.2.0
Summary: A FIFO accounting calculator
Home-page: https://github.com/vst/accfifo
Author: Vehbi Sinan Tunalioglu
Author-email: vst@vsthost.com
Keywords: accounting,fifo
Classifier: Development Status :: 3 - Alpha
Classifier: Intended Audience :: Developers
Classifier: Programming Language :: Python
Classifier: License :: OSI Approved :: BSD License
Classifier: Topic :: Software Development :: Libraries
License-File: LICENSE.txt
